{
  "amendment_event": {
    "affected_law_ids": [
      "355AC0000000060"
    ],
    "amendment_id": "promulgation:令和六年法律第四十号:令和六年五月二十九日",
    "amendment_law_name": "都市緑地法等の一部を改正する法律",
    "amendment_law_num": "令和六年法律第四十号",
    "amendment_promulgation_date": "令和六年五月二十九日",
    "group_key": "令和六年法律第四十号:令和六年五月二十九日"
  },
  "amendment_id": "promulgation:令和六年法律第四十号:令和六年五月二十九日",
  "effective_date": "令和六年十一月八日",
  "effective_note": "",
  "law_id": "355AC0000000060",
  "law_name": "明日香村における歴史的風土の保存及び生活環境の整備等に関する特別措置法",
  "law_num": "昭和五十五年法律第六十号",
  "law_type": "法律",
  "phase_index": 1,
  "projection": "promulgation",
  "revision_id": "20241108_506AC0000000040",
  "unit_id": "enforcement:355AC0000000060:20241108_506AC0000000040:p1"
}
