{
  "amendment_event": {
    "affected_law_ids": [
      "413AC0000000013"
    ],
    "amendment_id": "promulgation:平成十三年法律第百一号:平成十三年七月四日",
    "amendment_law_name": "厚生年金保険制度及び農林漁業団体職員共済組合制度の統合を図るための農林漁業団体職員共済組合法等を廃止する等の法律",
    "amendment_law_num": "平成十三年法律第百一号",
    "amendment_promulgation_date": "平成十三年七月四日",
    "group_key": "平成十三年法律第百一号:平成十三年七月四日"
  },
  "amendment_id": "promulgation:平成十三年法律第百一号:平成十三年七月四日",
  "effective_date": "平成十四年四月一日",
  "effective_note": "",
  "law_id": "413AC0000000013",
  "law_name": "平成十三年度における国民年金法による年金の額等の改定の特例に関する法律",
  "law_num": "平成十三年法律第十三号",
  "law_type": "法律",
  "phase_index": 1,
  "projection": "promulgation",
  "revision_id": "20020401_413AC0000000101",
  "unit_id": "enforcement:413AC0000000013:20020401_413AC0000000101:p1"
}
