{
  "amendment_event": {
    "affected_law_ids": [
      "346AC0000000089"
    ],
    "amendment_id": "promulgation:令和四年法律第四号:令和四年三月三十一日",
    "amendment_law_name": "所得税法等の一部を改正する法律",
    "amendment_law_num": "令和四年法律第四号",
    "amendment_promulgation_date": "令和四年三月三十一日",
    "group_key": "令和四年法律第四号:令和四年三月三十一日"
  },
  "amendment_id": "promulgation:令和四年法律第四号:令和四年三月三十一日",
  "effective_date": "令和四年四月一日",
  "effective_note": "",
  "law_id": "346AC0000000089",
  "law_name": "自動車重量税法",
  "law_num": "昭和四十六年法律第八十九号",
  "law_type": "法律",
  "phase_index": 1,
  "projection": "promulgation",
  "revision_id": "20220401_504AC0000000004",
  "unit_id": "enforcement:346AC0000000089:20220401_504AC0000000004:p1"
}
